wield/declarative/__init__.py
wield/declarative/_version.py
wield/declarative/metaclass.py
wield/declarative/overridable_object.py
wield/declarative/run.py
wield/declarative/argparse/__init__.py
wield/declarative/argparse/annotations.py
wield/declarative/argparse/oo_argparse.py
wield/declarative/callbacks/__init__.py
wield/declarative/callbacks/callbacks.py
wield/declarative/callbacks/relay.py
wield/declarative/callbacks/state_booleans.py
wield/declarative/callbacks/validators.py
wield/declarative/properties/__init__.py
wield/declarative/properties/bases.py
wield/declarative/properties/memoized.py
wield/declarative/properties/memoized_adv.py
wield/declarative/properties/memoized_adv_group.py
wield/declarative/properties/utilities.py
wield/declarative/utilities/__init__.py
wield/declarative/utilities/representations.py
wield/declarative/utilities/super_base.py
wield/declarative/utilities/unique.py
wield.declarative-1.5.1.dist-info/Apache-2.0.txt
wield.declarative-1.5.1.dist-info/CC0-1.0.txt
wield.declarative-1.5.1.dist-info/METADATA
wield.declarative-1.5.1.dist-info/NOTICE
wield.declarative-1.5.1.dist-info/WHEEL
wield.declarative-1.5.1.dist-info/top_level.txt
wield.declarative-1.5.1.dist-info/RECORD
