Metadata-Version: 2.1
Name: wield.declarative
Version: 1.5.1
Summary: Base classes and methods for declarative object instantiation
Home-page: https://github.com/wieldphysics/wield-declarative
Author: Lee McCuller
Author-email: mcculler@caltech.edu
License: Apache-2.0
Project-URL: Bug Tracker, https://github.com/wieldphysics/wield-declarative/issues
Project-URL: Source Code, https://github.com/wieldphysics/wield-declarative
Classifier: Intended Audience :: Science/Research
Classifier: License :: OSI Approved :: Apache Software License
Classifier: Operating System :: OS Independent
Classifier: Programming Language :: Python
Classifier: Programming Language :: Python :: 3
Classifier: Topic :: Scientific/Engineering :: Physics
License-File: LICENSES/Apache-2.0.txt
License-File: LICENSES/CC0-1.0.txt
License-File: NOTICE
Requires-Dist: numpy
